PDFraken/__init__.py
PDFraken/cli.py
PDFraken-0.1.1.dist-info/LICENSE
PDFraken-0.1.1.dist-info/METADATA
PDFraken-0.1.1.dist-info/WHEEL
PDFraken-0.1.1.dist-info/entry_points.txt
PDFraken-0.1.1.dist-info/top_level.txt
PDFraken-0.1.1.dist-info/RECORD
