Metadata-Version: 2.1
Name: PDFraken
Version: 0.1.1
Summary: Split your PDF from command line instead of sending your data to third parties
Home-page: https://github.com/patrickfleith/PDFraken
Author: Patrick Fleith
Author-email: 
License: UNKNOWN
Platform: UNKNOWN
License-File: LICENSE
Requires-Dist: typer
Requires-Dist: PyPDF2
